[
  {
    "acc_iid": 1.0,
    "acc_ood": 0.62,
    "auc_iid": 0.9347319347319347,
    "auc_ood": 0.8904991948470209,
    "mcc_iid": 0.4648740378581238,
    "mcc_ood": 0.47367492788947513,
    "method": "linear_probe",
    "num_latents": 100,
    "k": 10,
    "input_dim": 47,
    "width": 100,
    "n_samples": 100,
    "seed": 0
  },
  {
    "acc_iid": 1.0,
    "acc_ood": 0.58,
    "auc_iid": 0.8449883449883451,
    "auc_ood": 0.5330112721417068,
    "mcc_iid": 0.45084567144932636,
    "mcc_ood": 0.45725672208880935,
    "method": "sae_relu",
    "num_latents": 100,
    "k": 10,
    "input_dim": 47,
    "width": 100,
    "n_samples": 100,
    "seed": 0
  },
  {
    "acc_iid": 1.0,
    "acc_ood": 0.5,
    "auc_iid": 0.8601398601398602,
    "auc_ood": 0.5152979066022545,
    "mcc_iid": 0.5053243620048409,
    "mcc_ood": 0.46825705514598165,
    "method": "sae_topk",
    "num_latents": 100,
    "k": 10,
    "input_dim": 47,
    "width": 100,
    "n_samples": 100,
    "seed": 0
  },
  {
    "acc_iid": 1.0,
    "acc_ood": 0.58,
    "auc_iid": 0.8484848484848485,
    "auc_ood": 0.7713365539452496,
    "mcc_iid": 0.43989232506110226,
    "mcc_ood": 0.4512850878972742,
    "method": "sae_jumprelu",
    "num_latents": 100,
    "k": 10,
    "input_dim": 47,
    "width": 100,
    "n_samples": 100,
    "seed": 0
  },
  {
    "acc_iid": 1.0,
    "acc_ood": 0.58,
    "auc_iid": 0.6923076923076923,
    "auc_ood": 0.5297906602254429,
    "mcc_iid": 0.5162235797780622,
    "mcc_ood": 0.4550076207476181,
    "method": "sae_MP",
    "num_latents": 100,
    "k": 10,
    "input_dim": 47,
    "width": 100,
    "n_samples": 100,
    "seed": 0
  },
  {
    "acc_iid": 1.0,
    "acc_ood": 0.7,
    "auc_iid": 0.993006993006993,
    "auc_ood": 1.0,
    "mcc_iid": 0.9267498226510827,
    "mcc_ood": 0.9875831890557848,
    "method": "fista_oracle",
    "num_latents": 100,
    "k": 10,
    "input_dim": 47,
    "width": 100,
    "n_samples": 100,
    "seed": 0
  },
  {
    "acc_iid": 1.0,
    "acc_ood": 0.54,
    "auc_iid": 0.5454545454545454,
    "auc_ood": 0.5780998389694041,
    "mcc_iid": 0.3591284357092512,
    "mcc_ood": 0.4839474352714588,
    "method": "dl_fista",
    "num_latents": 100,
    "k": 10,
    "input_dim": 47,
    "width": 100,
    "n_samples": 100,
    "seed": 0
  },
  {
    "acc_iid": 1.0,
    "acc_ood": 0.56,
    "auc_iid": 0.9067599067599067,
    "auc_ood": 0.6682769726247988,
    "mcc_iid": 0.6030046888090004,
    "mcc_ood": 0.4691363566693727,
    "method": "softplus_adam",
    "num_latents": 100,
    "k": 10,
    "input_dim": 47,
    "width": 100,
    "n_samples": 100,
    "seed": 0
  },
  {
    "acc_iid": 1.0,
    "acc_ood": 0.64,
    "auc_iid": 0.9580952380952381,
    "auc_ood": 0.6843800322061191,
    "mcc_iid": 0.44295261333089875,
    "mcc_ood": 0.443448366963387,
    "method": "linear_probe",
    "num_latents": 100,
    "k": 10,
    "input_dim": 47,
    "width": 100,
    "n_samples": 100,
    "seed": 1
  },
  {
    "acc_iid": 1.0,
    "acc_ood": 0.66,
    "auc_iid": 0.8638095238095238,
    "auc_ood": 0.5201288244766505,
    "mcc_iid": 0.45115977987430084,
    "mcc_ood": 0.42933311260425516,
    "method": "sae_relu",
    "num_latents": 100,
    "k": 10,
    "input_dim": 47,
    "width": 100,
    "n_samples": 100,
    "seed": 1
  },
  {
    "acc_iid": 1.0,
    "acc_ood": 0.58,
    "auc_iid": 0.6876190476190476,
    "auc_ood": 0.5434782608695652,
    "mcc_iid": 0.47793626900812636,
    "mcc_ood": 0.4819536750935505,
    "method": "sae_topk",
    "num_latents": 100,
    "k": 10,
    "input_dim": 47,
    "width": 100,
    "n_samples": 100,
    "seed": 1
  },
  {
    "acc_iid": 1.0,
    "acc_ood": 0.68,
    "auc_iid": 0.8657142857142857,
    "auc_ood": 0.6417069243156199,
    "mcc_iid": 0.4404689793104833,
    "mcc_ood": 0.42820320366780534,
    "method": "sae_jumprelu",
    "num_latents": 100,
    "k": 10,
    "input_dim": 47,
    "width": 100,
    "n_samples": 100,
    "seed": 1
  },
  {
    "acc_iid": 1.0,
    "acc_ood": 0.56,
    "auc_iid": 0.6685714285714285,
    "auc_ood": 0.5869565217391304,
    "mcc_iid": 0.5302046371214586,
    "mcc_ood": 0.44755322240147233,
    "method": "sae_MP",
    "num_latents": 100,
    "k": 10,
    "input_dim": 47,
    "width": 100,
    "n_samples": 100,
    "seed": 1
  },
  {
    "acc_iid": 1.0,
    "acc_ood": 0.82,
    "auc_iid": 1.0,
    "auc_ood": 0.923510466988728,
    "mcc_iid": 0.9176169299970515,
    "mcc_ood": 0.9804480841857344,
    "method": "fista_oracle",
    "num_latents": 100,
    "k": 10,
    "input_dim": 47,
    "width": 100,
    "n_samples": 100,
    "seed": 1
  },
  {
    "acc_iid": 1.0,
    "acc_ood": 0.6,
    "auc_iid": 0.5333333333333333,
    "auc_ood": 0.6288244766505636,
    "mcc_iid": 0.3792866829943922,
    "mcc_ood": 0.4740757595162495,
    "method": "dl_fista",
    "num_latents": 100,
    "k": 10,
    "input_dim": 47,
    "width": 100,
    "n_samples": 100,
    "seed": 1
  },
  {
    "acc_iid": 1.0,
    "acc_ood": 0.56,
    "auc_iid": 0.939047619047619,
    "auc_ood": 0.639291465378422,
    "mcc_iid": 0.6198210889425741,
    "mcc_ood": 0.4723149424771809,
    "method": "softplus_adam",
    "num_latents": 100,
    "k": 10,
    "input_dim": 47,
    "width": 100,
    "n_samples": 100,
    "seed": 1
  },
  {
    "acc_iid": 1.0,
    "acc_ood": 0.68,
    "auc_iid": 0.9401993355481727,
    "auc_ood": 0.8768472906403941,
    "mcc_iid": 0.4441377871674477,
    "mcc_ood": 0.45912929682751996,
    "method": "linear_probe",
    "num_latents": 100,
    "k": 10,
    "input_dim": 47,
    "width": 100,
    "n_samples": 100,
    "seed": 2
  },
  {
    "acc_iid": 1.0,
    "acc_ood": 0.74,
    "auc_iid": 0.8770764119601329,
    "auc_ood": 0.6436781609195402,
    "mcc_iid": 0.457492993886701,
    "mcc_ood": 0.4517568346123663,
    "method": "sae_relu",
    "num_latents": 100,
    "k": 10,
    "input_dim": 47,
    "width": 100,
    "n_samples": 100,
    "seed": 2
  },
  {
    "acc_iid": 1.0,
    "acc_ood": 0.56,
    "auc_iid": 0.8073089700996678,
    "auc_ood": 0.5665024630541872,
    "mcc_iid": 0.4533117198059003,
    "mcc_ood": 0.4868966974872668,
    "method": "sae_topk",
    "num_latents": 100,
    "k": 10,
    "input_dim": 47,
    "width": 100,
    "n_samples": 100,
    "seed": 2
  },
  {
    "acc_iid": 1.0,
    "acc_ood": 0.8,
    "auc_iid": 0.8637873754152824,
    "auc_ood": 0.6510673234811166,
    "mcc_iid": 0.4463726642601199,
    "mcc_ood": 0.4446462611373254,
    "method": "sae_jumprelu",
    "num_latents": 100,
    "k": 10,
    "input_dim": 47,
    "width": 100,
    "n_samples": 100,
    "seed": 2
  },
  {
    "acc_iid": 1.0,
    "acc_ood": 0.42,
    "auc_iid": 0.7209302325581395,
    "auc_ood": 0.5123152709359606,
    "mcc_iid": 0.5357630977253459,
    "mcc_ood": 0.47792522091088074,
    "method": "sae_MP",
    "num_latents": 100,
    "k": 10,
    "input_dim": 47,
    "width": 100,
    "n_samples": 100,
    "seed": 2
  },
  {
    "acc_iid": 1.0,
    "acc_ood": 0.9,
    "auc_iid": 1.0,
    "auc_ood": 1.0,
    "mcc_iid": 0.9797485939421057,
    "mcc_ood": 0.9884333290635774,
    "method": "fista_oracle",
    "num_latents": 100,
    "k": 10,
    "input_dim": 47,
    "width": 100,
    "n_samples": 100,
    "seed": 2
  },
  {
    "acc_iid": 1.0,
    "acc_ood": 0.48,
    "auc_iid": 0.5714285714285714,
    "auc_ood": 0.6880131362889983,
    "mcc_iid": 0.3722259180369724,
    "mcc_ood": 0.4969696395231671,
    "method": "dl_fista",
    "num_latents": 100,
    "k": 10,
    "input_dim": 47,
    "width": 100,
    "n_samples": 100,
    "seed": 2
  },
  {
    "acc_iid": 1.0,
    "acc_ood": 0.68,
    "auc_iid": 0.8870431893687707,
    "auc_ood": 0.607553366174056,
    "mcc_iid": 0.6386798212635776,
    "mcc_ood": 0.4646367806148857,
    "method": "softplus_adam",
    "num_latents": 100,
    "k": 10,
    "input_dim": 47,
    "width": 100,
    "n_samples": 100,
    "seed": 2
  },
  {
    "acc_iid": 1.0,
    "acc_ood": 0.652,
    "auc_iid": 0.9700027270248159,
    "auc_ood": 0.897842190016103,
    "mcc_iid": 0.5944510005112312,
    "mcc_ood": 0.4048178949769896,
    "method": "linear_probe",
    "num_latents": 100,
    "k": 10,
    "input_dim": 47,
    "width": 100,
    "n_samples": 500,
    "seed": 0
  },
  {
    "acc_iid": 1.0,
    "acc_ood": 0.6,
    "auc_iid": 0.7879283701481684,
    "auc_ood": 0.6623510466988729,
    "mcc_iid": 0.3153414314440133,
    "mcc_ood": 0.357218125726007,
    "method": "sae_relu",
    "num_latents": 100,
    "k": 10,
    "input_dim": 47,
    "width": 100,
    "n_samples": 500,
    "seed": 0
  },
  {
    "acc_iid": 1.0,
    "acc_ood": 0.668,
    "auc_iid": 0.6200345423143351,
    "auc_ood": 0.6640901771336554,
    "mcc_iid": 0.34902795795297775,
    "mcc_ood": 0.3446165298809512,
    "method": "sae_topk",
    "num_latents": 100,
    "k": 10,
    "input_dim": 47,
    "width": 100,
    "n_samples": 500,
    "seed": 0
  },
  {
    "acc_iid": 1.0,
    "acc_ood": 0.628,
    "auc_iid": 0.8143805108626488,
    "auc_ood": 0.7857004830917875,
    "mcc_iid": 0.2972238760252498,
    "mcc_ood": 0.34300497177213934,
    "method": "sae_jumprelu",
    "num_latents": 100,
    "k": 10,
    "input_dim": 47,
    "width": 100,
    "n_samples": 500,
    "seed": 0
  },
  {
    "acc_iid": 1.0,
    "acc_ood": 0.584,
    "auc_iid": 0.608490137260249,
    "auc_ood": 0.5308856682769727,
    "mcc_iid": 0.2730074599712244,
    "mcc_ood": 0.2755751464060153,
    "method": "sae_MP",
    "num_latents": 100,
    "k": 10,
    "input_dim": 47,
    "width": 100,
    "n_samples": 500,
    "seed": 0
  },
  {
    "acc_iid": 1.0,
    "acc_ood": 0.912,
    "auc_iid": 0.9977274793200619,
    "auc_ood": 0.9914975845410627,
    "mcc_iid": 0.9865934020805684,
    "mcc_ood": 0.9852904129654493,
    "method": "fista_oracle",
    "num_latents": 100,
    "k": 10,
    "input_dim": 47,
    "width": 100,
    "n_samples": 500,
    "seed": 0
  },
  {
    "acc_iid": 1.0,
    "acc_ood": 0.572,
    "auc_iid": 0.7572947913826016,
    "auc_ood": 0.5576167471819645,
    "mcc_iid": 0.4844889337104973,
    "mcc_ood": 0.43799411583166714,
    "method": "dl_fista",
    "num_latents": 100,
    "k": 10,
    "input_dim": 47,
    "width": 100,
    "n_samples": 500,
    "seed": 0
  },
  {
    "acc_iid": 0.972,
    "acc_ood": 0.528,
    "auc_iid": 0.813562403417871,
    "auc_ood": 0.7120128824476651,
    "mcc_iid": 0.4170774275567034,
    "mcc_ood": 0.3692544480900314,
    "method": "softplus_adam",
    "num_latents": 100,
    "k": 10,
    "input_dim": 47,
    "width": 100,
    "n_samples": 500,
    "seed": 0
  },
  {
    "acc_iid": 1.0,
    "acc_ood": 0.692,
    "auc_iid": 0.9763251454427926,
    "auc_ood": 0.826496,
    "mcc_iid": 0.594299482447234,
    "mcc_ood": 0.42844046427413474,
    "method": "linear_probe",
    "num_latents": 100,
    "k": 10,
    "input_dim": 47,
    "width": 100,
    "n_samples": 500,
    "seed": 1
  },
  {
    "acc_iid": 1.0,
    "acc_ood": 0.668,
    "auc_iid": 0.7823610213316097,
    "auc_ood": 0.7628159999999999,
    "mcc_iid": 0.31345094402428736,
    "mcc_ood": 0.3620172024400657,
    "method": "sae_relu",
    "num_latents": 100,
    "k": 10,
    "input_dim": 47,
    "width": 100,
    "n_samples": 500,
    "seed": 1
  },
  {
    "acc_iid": 1.0,
    "acc_ood": 0.612,
    "auc_iid": 0.6363930187459599,
    "auc_ood": 0.508,
    "mcc_iid": 0.3555715493700631,
    "mcc_ood": 0.34971868314207205,
    "method": "sae_topk",
    "num_latents": 100,
    "k": 10,
    "input_dim": 47,
    "width": 100,
    "n_samples": 500,
    "seed": 1
  },
  {
    "acc_iid": 1.0,
    "acc_ood": 0.656,
    "auc_iid": 0.8082579185520362,
    "auc_ood": 0.7343360000000001,
    "mcc_iid": 0.29855377804297156,
    "mcc_ood": 0.35760070343730377,
    "method": "sae_jumprelu",
    "num_latents": 100,
    "k": 10,
    "input_dim": 47,
    "width": 100,
    "n_samples": 500,
    "seed": 1
  },
  {
    "acc_iid": 1.0,
    "acc_ood": 0.62,
    "auc_iid": 0.6040723981900453,
    "auc_ood": 0.647232,
    "mcc_iid": 0.281555838787946,
    "mcc_ood": 0.2822044134694413,
    "method": "sae_MP",
    "num_latents": 100,
    "k": 10,
    "input_dim": 47,
    "width": 100,
    "n_samples": 500,
    "seed": 1
  },
  {
    "acc_iid": 1.0,
    "acc_ood": 0.868,
    "auc_iid": 0.9969295410471881,
    "auc_ood": 0.974592,
    "mcc_iid": 0.9865224726903117,
    "mcc_ood": 0.9825368051322627,
    "method": "fista_oracle",
    "num_latents": 100,
    "k": 10,
    "input_dim": 47,
    "width": 100,
    "n_samples": 500,
    "seed": 1
  },
  {
    "acc_iid": 1.0,
    "acc_ood": 0.684,
    "auc_iid": 0.7592921784098255,
    "auc_ood": 0.7369600000000001,
    "mcc_iid": 0.5644109545162093,
    "mcc_ood": 0.41248018175228757,
    "method": "dl_fista",
    "num_latents": 100,
    "k": 10,
    "input_dim": 47,
    "width": 100,
    "n_samples": 500,
    "seed": 1
  },
  {
    "acc_iid": 0.952,
    "acc_ood": 0.62,
    "auc_iid": 0.809793148028442,
    "auc_ood": 0.6793600000000001,
    "mcc_iid": 0.41070998268634484,
    "mcc_ood": 0.3646156316389466,
    "method": "softplus_adam",
    "num_latents": 100,
    "k": 10,
    "input_dim": 47,
    "width": 100,
    "n_samples": 500,
    "seed": 1
  },
  {
    "acc_iid": 1.0,
    "acc_ood": 0.736,
    "auc_iid": 0.9816310231608838,
    "auc_ood": 0.859698985853627,
    "mcc_iid": 0.5848491534824194,
    "mcc_ood": 0.45585641575769936,
    "method": "linear_probe",
    "num_latents": 100,
    "k": 10,
    "input_dim": 47,
    "width": 100,
    "n_samples": 500,
    "seed": 2
  },
  {
    "acc_iid": 1.0,
    "acc_ood": 0.764,
    "auc_iid": 0.7236666962463396,
    "auc_ood": 0.7522769846909114,
    "mcc_iid": 0.3153543701975494,
    "mcc_ood": 0.3613122974559996,
    "method": "sae_relu",
    "num_latents": 100,
    "k": 10,
    "input_dim": 47,
    "width": 100,
    "n_samples": 500,
    "seed": 2
  },
  {
    "acc_iid": 1.0,
    "acc_ood": 0.552,
    "auc_iid": 0.6757476262312538,
    "auc_ood": 0.5904011368774628,
    "mcc_iid": 0.33346978417244805,
    "mcc_ood": 0.33231827967769123,
    "method": "sae_topk",
    "num_latents": 100,
    "k": 10,
    "input_dim": 47,
    "width": 100,
    "n_samples": 500,
    "seed": 2
  },
  {
    "acc_iid": 1.0,
    "acc_ood": 0.76,
    "auc_iid": 0.752063182181205,
    "auc_ood": 0.6816743104450617,
    "mcc_iid": 0.2921674358084352,
    "mcc_ood": 0.3504113222610539,
    "method": "sae_jumprelu",
    "num_latents": 100,
    "k": 10,
    "input_dim": 47,
    "width": 100,
    "n_samples": 500,
    "seed": 2
  },
  {
    "acc_iid": 1.0,
    "acc_ood": 0.672,
    "auc_iid": 0.5954388144467123,
    "auc_ood": 0.5124668949034301,
    "mcc_iid": 0.2780139580792481,
    "mcc_ood": 0.27763968396452077,
    "method": "sae_MP",
    "num_latents": 100,
    "k": 10,
    "input_dim": 47,
    "width": 100,
    "n_samples": 500,
    "seed": 2
  },
  {
    "acc_iid": 1.0,
    "acc_ood": 0.948,
    "auc_iid": 0.9975153074806993,
    "auc_ood": 0.9928299205477682,
    "mcc_iid": 0.9838085830584703,
    "mcc_ood": 0.989645739911423,
    "method": "fista_oracle",
    "num_latents": 100,
    "k": 10,
    "input_dim": 47,
    "width": 100,
    "n_samples": 500,
    "seed": 2
  },
  {
    "acc_iid": 1.0,
    "acc_ood": 0.672,
    "auc_iid": 0.6838672464282545,
    "auc_ood": 0.6722433951295136,
    "mcc_iid": 0.4785384024366233,
    "mcc_ood": 0.3972718027597639,
    "method": "dl_fista",
    "num_latents": 100,
    "k": 10,
    "input_dim": 47,
    "width": 100,
    "n_samples": 500,
    "seed": 2
  },
  {
    "acc_iid": 0.944,
    "acc_ood": 0.696,
    "auc_iid": 0.7271275179696511,
    "auc_ood": 0.6405270977327046,
    "mcc_iid": 0.43092107449042116,
    "mcc_ood": 0.3628550018683434,
    "method": "softplus_adam",
    "num_latents": 100,
    "k": 10,
    "input_dim": 47,
    "width": 100,
    "n_samples": 500,
    "seed": 2
  },
  {
    "acc_iid": 1.0,
    "acc_ood": 0.594,
    "auc_iid": 0.9759782700959172,
    "auc_ood": 0.9051675731177103,
    "mcc_iid": 0.633736371708736,
    "mcc_ood": 0.4307573093262687,
    "method": "linear_probe",
    "num_latents": 100,
    "k": 10,
    "input_dim": 47,
    "width": 100,
    "n_samples": 1000,
    "seed": 0
  },
  {
    "acc_iid": 1.0,
    "acc_ood": 0.62,
    "auc_iid": 0.8432009167303284,
    "auc_ood": 0.7186953522324366,
    "mcc_iid": 0.3183809957203798,
    "mcc_ood": 0.36129149668352484,
    "method": "sae_relu",
    "num_latents": 100,
    "k": 10,
    "input_dim": 47,
    "width": 100,
    "n_samples": 1000,
    "seed": 0
  },
  {
    "acc_iid": 1.0,
    "acc_ood": 0.606,
    "auc_iid": 0.7012562600797895,
    "auc_ood": 0.6650382634644078,
    "mcc_iid": 0.36179825071943983,
    "mcc_ood": 0.3629868681983765,
    "method": "sae_topk",
    "num_latents": 100,
    "k": 10,
    "input_dim": 47,
    "width": 100,
    "n_samples": 1000,
    "seed": 0
  },
  {
    "acc_iid": 1.0,
    "acc_ood": 0.586,
    "auc_iid": 0.8625541125541126,
    "auc_ood": 0.7252891819479873,
    "mcc_iid": 0.27392270356058146,
    "mcc_ood": 0.3344063434203363,
    "method": "sae_jumprelu",
    "num_latents": 100,
    "k": 10,
    "input_dim": 47,
    "width": 100,
    "n_samples": 1000,
    "seed": 0
  },
  {
    "acc_iid": 1.0,
    "acc_ood": 0.574,
    "auc_iid": 0.606272812155165,
    "auc_ood": 0.5383517030049254,
    "mcc_iid": 0.23545868536329084,
    "mcc_ood": 0.2456877320487479,
    "method": "sae_MP",
    "num_latents": 100,
    "k": 10,
    "input_dim": 47,
    "width": 100,
    "n_samples": 1000,
    "seed": 0
  },
  {
    "acc_iid": 1.0,
    "acc_ood": 0.934,
    "auc_iid": 0.9952465834818776,
    "auc_ood": 0.994817987839117,
    "mcc_iid": 0.9861360077574964,
    "mcc_ood": 0.9871602979836385,
    "method": "fista_oracle",
    "num_latents": 100,
    "k": 10,
    "input_dim": 47,
    "width": 100,
    "n_samples": 1000,
    "seed": 0
  },
  {
    "acc_iid": 1.0,
    "acc_ood": 0.872,
    "auc_iid": 0.9785035226211697,
    "auc_ood": 0.9736567679004027,
    "mcc_iid": 0.9433623551107024,
    "mcc_ood": 0.9362118748561862,
    "method": "dl_fista",
    "num_latents": 100,
    "k": 10,
    "input_dim": 47,
    "width": 100,
    "n_samples": 1000,
    "seed": 0
  },
  {
    "acc_iid": 0.968,
    "acc_ood": 0.54,
    "auc_iid": 0.7677404295051353,
    "auc_ood": 0.6157449744108069,
    "mcc_iid": 0.4374660662271196,
    "mcc_ood": 0.3519045028435832,
    "method": "softplus_adam",
    "num_latents": 100,
    "k": 10,
    "input_dim": 47,
    "width": 100,
    "n_samples": 1000,
    "seed": 0
  },
  {
    "acc_iid": 1.0,
    "acc_ood": 0.684,
    "auc_iid": 0.9825757074483337,
    "auc_ood": 0.859816384180791,
    "mcc_iid": 0.6383464601657077,
    "mcc_ood": 0.41031320884206024,
    "method": "linear_probe",
    "num_latents": 100,
    "k": 10,
    "input_dim": 47,
    "width": 100,
    "n_samples": 1000,
    "seed": 1
  },
  {
    "acc_iid": 1.0,
    "acc_ood": 0.664,
    "auc_iid": 0.7452303756148129,
    "auc_ood": 0.6702458911145351,
    "mcc_iid": 0.3192270233359382,
    "mcc_ood": 0.36159710605645135,
    "method": "sae_relu",
    "num_latents": 100,
    "k": 10,
    "input_dim": 47,
    "width": 100,
    "n_samples": 1000,
    "seed": 1
  },
  {
    "acc_iid": 0.962,
    "acc_ood": 0.61,
    "auc_iid": 0.6481616268554666,
    "auc_ood": 0.5278794298921416,
    "mcc_iid": 0.3618119558742944,
    "mcc_ood": 0.3410354813197927,
    "method": "sae_topk",
    "num_latents": 100,
    "k": 10,
    "input_dim": 47,
    "width": 100,
    "n_samples": 1000,
    "seed": 1
  },
  {
    "acc_iid": 1.0,
    "acc_ood": 0.666,
    "auc_iid": 0.7706610203136373,
    "auc_ood": 0.7125224704673857,
    "mcc_iid": 0.2800481049280159,
    "mcc_ood": 0.3345418735099203,
    "method": "sae_jumprelu",
    "num_latents": 100,
    "k": 10,
    "input_dim": 47,
    "width": 100,
    "n_samples": 1000,
    "seed": 1
  },
  {
    "acc_iid": 1.0,
    "acc_ood": 0.678,
    "auc_iid": 0.5841990339442864,
    "auc_ood": 0.5354391371340523,
    "mcc_iid": 0.2372049733762281,
    "mcc_ood": 0.26866235826193785,
    "method": "sae_MP",
    "num_latents": 100,
    "k": 10,
    "input_dim": 47,
    "width": 100,
    "n_samples": 1000,
    "seed": 1
  },
  {
    "acc_iid": 1.0,
    "acc_ood": 0.914,
    "auc_iid": 0.9980590661461435,
    "auc_ood": 0.9798407806882383,
    "mcc_iid": 0.9864861630155438,
    "mcc_ood": 0.982836282341391,
    "method": "fista_oracle",
    "num_latents": 100,
    "k": 10,
    "input_dim": 47,
    "width": 100,
    "n_samples": 1000,
    "seed": 1
  },
  {
    "acc_iid": 1.0,
    "acc_ood": 0.818,
    "auc_iid": 0.8780299521383357,
    "auc_ood": 0.9326848998459167,
    "mcc_iid": 0.929916800179848,
    "mcc_ood": 0.9222359249384368,
    "method": "dl_fista",
    "num_latents": 100,
    "k": 10,
    "input_dim": 47,
    "width": 100,
    "n_samples": 1000,
    "seed": 1
  },
  {
    "acc_iid": 0.984,
    "acc_ood": 0.59,
    "auc_iid": 0.7308498202430579,
    "auc_ood": 0.7322804314329738,
    "mcc_iid": 0.4615988321773846,
    "mcc_ood": 0.3851648835744227,
    "method": "softplus_adam",
    "num_latents": 100,
    "k": 10,
    "input_dim": 47,
    "width": 100,
    "n_samples": 1000,
    "seed": 1
  },
  {
    "acc_iid": 1.0,
    "acc_ood": 0.684,
    "auc_iid": 0.9791127989657401,
    "auc_ood": 0.893200620889408,
    "mcc_iid": 0.6334971511629464,
    "mcc_ood": 0.4308799688318722,
    "method": "linear_probe",
    "num_latents": 100,
    "k": 10,
    "input_dim": 47,
    "width": 100,
    "n_samples": 1000,
    "seed": 2
  },
  {
    "acc_iid": 1.0,
    "acc_ood": 0.73,
    "auc_iid": 0.7291329993535877,
    "auc_ood": 0.6329071386279624,
    "mcc_iid": 0.31603019697262097,
    "mcc_ood": 0.3532513272196657,
    "method": "sae_relu",
    "num_latents": 100,
    "k": 10,
    "input_dim": 47,
    "width": 100,
    "n_samples": 1000,
    "seed": 2
  },
  {
    "acc_iid": 0.942,
    "acc_ood": 0.634,
    "auc_iid": 0.6461498060762768,
    "auc_ood": 0.5839640908290794,
    "mcc_iid": 0.33001414616567865,
    "mcc_ood": 0.33769338373604824,
    "method": "sae_topk",
    "num_latents": 100,
    "k": 10,
    "input_dim": 47,
    "width": 100,
    "n_samples": 1000,
    "seed": 2
  },
  {
    "acc_iid": 1.0,
    "acc_ood": 0.696,
    "auc_iid": 0.7350921137685844,
    "auc_ood": 0.6858107567489717,
    "mcc_iid": 0.2719845066197153,
    "mcc_ood": 0.32885887260892366,
    "method": "sae_jumprelu",
    "num_latents": 100,
    "k": 10,
    "input_dim": 47,
    "width": 100,
    "n_samples": 1000,
    "seed": 2
  },
  {
    "acc_iid": 1.0,
    "acc_ood": 0.656,
    "auc_iid": 0.5939722042663218,
    "auc_ood": 0.589724920388536,
    "mcc_iid": 0.24347848266635203,
    "mcc_ood": 0.2638392173576,
    "method": "sae_MP",
    "num_latents": 100,
    "k": 10,
    "input_dim": 47,
    "width": 100,
    "n_samples": 1000,
    "seed": 2
  },
  {
    "acc_iid": 1.0,
    "acc_ood": 0.81,
    "auc_iid": 0.9972729476405948,
    "auc_ood": 0.9960474308300395,
    "mcc_iid": 0.983631239039495,
    "mcc_ood": 0.9878166921684075,
    "method": "fista_oracle",
    "num_latents": 100,
    "k": 10,
    "input_dim": 47,
    "width": 100,
    "n_samples": 1000,
    "seed": 2
  },
  {
    "acc_iid": 1.0,
    "acc_ood": 0.84,
    "auc_iid": 0.8315186651583711,
    "auc_ood": 0.9184842617336897,
    "mcc_iid": 0.883777496243481,
    "mcc_ood": 0.8258887343192755,
    "method": "dl_fista",
    "num_latents": 100,
    "k": 10,
    "input_dim": 47,
    "width": 100,
    "n_samples": 1000,
    "seed": 2
  },
  {
    "acc_iid": 0.968,
    "acc_ood": 0.722,
    "auc_iid": 0.7488485778926955,
    "auc_ood": 0.6447808484421756,
    "mcc_iid": 0.43836506836603134,
    "mcc_ood": 0.38164656728827084,
    "method": "softplus_adam",
    "num_latents": 100,
    "k": 10,
    "input_dim": 47,
    "width": 100,
    "n_samples": 1000,
    "seed": 2
  },
  {
    "acc_iid": 0.9632,
    "acc_ood": 0.598,
    "auc_iid": 0.9830779979891276,
    "auc_ood": 0.8981689665787919,
    "mcc_iid": 0.6708201171927396,
    "mcc_ood": 0.4305621505607446,
    "method": "linear_probe",
    "num_latents": 100,
    "k": 10,
    "input_dim": 47,
    "width": 100,
    "n_samples": 5000,
    "seed": 0
  },
  {
    "acc_iid": 0.982,
    "acc_ood": 0.5584,
    "auc_iid": 0.8931304761964556,
    "auc_ood": 0.8512913364963126,
    "mcc_iid": 0.4082560447583942,
    "mcc_ood": 0.42765469752153196,
    "method": "sae_relu",
    "num_latents": 100,
    "k": 10,
    "input_dim": 47,
    "width": 100,
    "n_samples": 5000,
    "seed": 0
  },
  {
    "acc_iid": 0.9864,
    "acc_ood": 0.6536,
    "auc_iid": 0.9820115719335317,
    "auc_ood": 0.8040328944715708,
    "mcc_iid": 0.8141531029572786,
    "mcc_ood": 0.6997094252117442,
    "method": "sae_topk",
    "num_latents": 100,
    "k": 10,
    "input_dim": 47,
    "width": 100,
    "n_samples": 5000,
    "seed": 0
  },
  {
    "acc_iid": 0.9636,
    "acc_ood": 0.598,
    "auc_iid": 0.8485522526344491,
    "auc_ood": 0.7756560045723033,
    "mcc_iid": 0.25247658279893287,
    "mcc_ood": 0.32106420718262446,
    "method": "sae_jumprelu",
    "num_latents": 100,
    "k": 10,
    "input_dim": 47,
    "width": 100,
    "n_samples": 5000,
    "seed": 0
  },
  {
    "acc_iid": 0.948,
    "acc_ood": 0.5812,
    "auc_iid": 0.6890592220740327,
    "auc_ood": 0.6007042780861608,
    "mcc_iid": 0.4936083936901735,
    "mcc_ood": 0.36923552820848604,
    "method": "sae_MP",
    "num_latents": 100,
    "k": 10,
    "input_dim": 47,
    "width": 100,
    "n_samples": 5000,
    "seed": 0
  },
  {
    "acc_iid": 0.9964,
    "acc_ood": 0.9272,
    "auc_iid": 0.9980904784925453,
    "auc_ood": 0.9925015248478193,
    "mcc_iid": 0.9863178945946917,
    "mcc_ood": 0.9856699294296355,
    "method": "fista_oracle",
    "num_latents": 100,
    "k": 10,
    "input_dim": 47,
    "width": 100,
    "n_samples": 5000,
    "seed": 0
  },
  {
    "acc_iid": 0.996,
    "acc_ood": 0.9184,
    "auc_iid": 0.9939207436460649,
    "auc_ood": 0.986579419130584,
    "mcc_iid": 0.9711503415978007,
    "mcc_ood": 0.9789631650057077,
    "method": "dl_fista",
    "num_latents": 100,
    "k": 10,
    "input_dim": 47,
    "width": 100,
    "n_samples": 5000,
    "seed": 0
  },
  {
    "acc_iid": 0.9652,
    "acc_ood": 0.5904,
    "auc_iid": 0.8327971306053517,
    "auc_ood": 0.7228527486621981,
    "mcc_iid": 0.6244407709484985,
    "mcc_ood": 0.42399518478367804,
    "method": "softplus_adam",
    "num_latents": 100,
    "k": 10,
    "input_dim": 47,
    "width": 100,
    "n_samples": 5000,
    "seed": 0
  },
  {
    "acc_iid": 0.9656,
    "acc_ood": 0.682,
    "auc_iid": 0.9832745237628495,
    "auc_ood": 0.8694082585719551,
    "mcc_iid": 0.6703647498676065,
    "mcc_ood": 0.38305911522783564,
    "method": "linear_probe",
    "num_latents": 100,
    "k": 10,
    "input_dim": 47,
    "width": 100,
    "n_samples": 5000,
    "seed": 1
  },
  {
    "acc_iid": 0.9796,
    "acc_ood": 0.6048,
    "auc_iid": 0.895807324714808,
    "auc_ood": 0.8389653998197535,
    "mcc_iid": 0.39230032859185493,
    "mcc_ood": 0.3971609828946207,
    "method": "sae_relu",
    "num_latents": 100,
    "k": 10,
    "input_dim": 47,
    "width": 100,
    "n_samples": 5000,
    "seed": 1
  },
  {
    "acc_iid": 0.988,
    "acc_ood": 0.7176,
    "auc_iid": 0.9861707231513677,
    "auc_ood": 0.8118554391462864,
    "mcc_iid": 0.8309014016257629,
    "mcc_ood": 0.749492398507524,
    "method": "sae_topk",
    "num_latents": 100,
    "k": 10,
    "input_dim": 47,
    "width": 100,
    "n_samples": 5000,
    "seed": 1
  },
  {
    "acc_iid": 0.9648,
    "acc_ood": 0.6868,
    "auc_iid": 0.7911675591276925,
    "auc_ood": 0.7034194369341691,
    "mcc_iid": 0.2552309149510171,
    "mcc_ood": 0.32822960139258833,
    "method": "sae_jumprelu",
    "num_latents": 100,
    "k": 10,
    "input_dim": 47,
    "width": 100,
    "n_samples": 5000,
    "seed": 1
  },
  {
    "acc_iid": 0.9344,
    "acc_ood": 0.6572,
    "auc_iid": 0.5705426816476309,
    "auc_ood": 0.591495637212732,
    "mcc_iid": 0.4141588547255883,
    "mcc_ood": 0.3385948623905081,
    "method": "sae_MP",
    "num_latents": 100,
    "k": 10,
    "input_dim": 47,
    "width": 100,
    "n_samples": 5000,
    "seed": 1
  },
  {
    "acc_iid": 0.992,
    "acc_ood": 0.9236,
    "auc_iid": 0.9984326045761411,
    "auc_ood": 0.9819951814755643,
    "mcc_iid": 0.9866614030530453,
    "mcc_ood": 0.9829890546112272,
    "method": "fista_oracle",
    "num_latents": 100,
    "k": 10,
    "input_dim": 47,
    "width": 100,
    "n_samples": 5000,
    "seed": 1
  },
  {
    "acc_iid": 0.994,
    "acc_ood": 0.894,
    "auc_iid": 0.9561241053895015,
    "auc_ood": 0.9618547350579657,
    "mcc_iid": 0.9561294570805211,
    "mcc_ood": 0.9441080529692957,
    "method": "dl_fista",
    "num_latents": 100,
    "k": 10,
    "input_dim": 47,
    "width": 100,
    "n_samples": 5000,
    "seed": 1
  },
  {
    "acc_iid": 0.9168,
    "acc_ood": 0.5172,
    "auc_iid": 0.7726029941293604,
    "auc_ood": 0.6987922965056736,
    "mcc_iid": 0.5712145425493561,
    "mcc_ood": 0.3939259237054382,
    "method": "softplus_adam",
    "num_latents": 100,
    "k": 10,
    "input_dim": 47,
    "width": 100,
    "n_samples": 5000,
    "seed": 1
  },
  {
    "acc_iid": 0.9616,
    "acc_ood": 0.75,
    "auc_iid": 0.9863655098220024,
    "auc_ood": 0.888571435886014,
    "mcc_iid": 0.6695811017999544,
    "mcc_ood": 0.4103004156546871,
    "method": "linear_probe",
    "num_latents": 100,
    "k": 10,
    "input_dim": 47,
    "width": 100,
    "n_samples": 5000,
    "seed": 2
  },
  {
    "acc_iid": 0.968,
    "acc_ood": 0.7464,
    "auc_iid": 0.8814627169083746,
    "auc_ood": 0.8316494243604218,
    "mcc_iid": 0.3982871692124288,
    "mcc_ood": 0.41394631659776426,
    "method": "sae_relu",
    "num_latents": 100,
    "k": 10,
    "input_dim": 47,
    "width": 100,
    "n_samples": 5000,
    "seed": 2
  },
  {
    "acc_iid": 0.992,
    "acc_ood": 0.7176,
    "auc_iid": 0.9805917651661218,
    "auc_ood": 0.8779710016922294,
    "mcc_iid": 0.7924779103694027,
    "mcc_ood": 0.6649745980771746,
    "method": "sae_topk",
    "num_latents": 100,
    "k": 10,
    "input_dim": 47,
    "width": 100,
    "n_samples": 5000,
    "seed": 2
  },
  {
    "acc_iid": 0.9596,
    "acc_ood": 0.7496,
    "auc_iid": 0.7428731976695448,
    "auc_ood": 0.6971687160306086,
    "mcc_iid": 0.2491856630590265,
    "mcc_ood": 0.32317970503063315,
    "method": "sae_jumprelu",
    "num_latents": 100,
    "k": 10,
    "input_dim": 47,
    "width": 100,
    "n_samples": 5000,
    "seed": 2
  },
  {
    "acc_iid": 0.9304,
    "acc_ood": 0.7644,
    "auc_iid": 0.6100561132534161,
    "auc_ood": 0.6283502172248975,
    "mcc_iid": 0.3917557285641133,
    "mcc_ood": 0.340626883781275,
    "method": "sae_MP",
    "num_latents": 100,
    "k": 10,
    "input_dim": 47,
    "width": 100,
    "n_samples": 5000,
    "seed": 2
  },
  {
    "acc_iid": 0.994,
    "acc_ood": 0.8944,
    "auc_iid": 0.9981653603263756,
    "auc_ood": 0.9960587185651124,
    "mcc_iid": 0.98459148389706,
    "mcc_ood": 0.988210447698327,
    "method": "fista_oracle",
    "num_latents": 100,
    "k": 10,
    "input_dim": 47,
    "width": 100,
    "n_samples": 5000,
    "seed": 2
  },
  {
    "acc_iid": 0.9924,
    "acc_ood": 0.8496,
    "auc_iid": 0.7704491156006371,
    "auc_ood": 0.7598685642163904,
    "mcc_iid": 0.9244494401166012,
    "mcc_ood": 0.9132268614519187,
    "method": "dl_fista",
    "num_latents": 100,
    "k": 10,
    "input_dim": 47,
    "width": 100,
    "n_samples": 5000,
    "seed": 2
  },
  {
    "acc_iid": 0.9212,
    "acc_ood": 0.6464,
    "auc_iid": 0.8200979056640679,
    "auc_ood": 0.7700654618813186,
    "mcc_iid": 0.5716056686061943,
    "mcc_ood": 0.4007877860447606,
    "method": "softplus_adam",
    "num_latents": 100,
    "k": 10,
    "input_dim": 47,
    "width": 100,
    "n_samples": 5000,
    "seed": 2
  },
  {
    "acc_iid": 0.954,
    "acc_ood": 0.6348,
    "auc_iid": 0.9793786337209303,
    "auc_ood": 0.903945162835249,
    "mcc_iid": 0.6757182139431857,
    "mcc_ood": 0.43352457574669634,
    "method": "linear_probe",
    "num_latents": 100,
    "k": 10,
    "input_dim": 47,
    "width": 100,
    "n_samples": 10000,
    "seed": 0
  },
  {
    "acc_iid": 0.9746,
    "acc_ood": 0.5676,
    "auc_iid": 0.9143865357599867,
    "auc_ood": 0.9104401328190628,
    "mcc_iid": 0.4286125040053843,
    "mcc_ood": 0.43230650398559434,
    "method": "sae_relu",
    "num_latents": 100,
    "k": 10,
    "input_dim": 47,
    "width": 100,
    "n_samples": 10000,
    "seed": 0
  },
  {
    "acc_iid": 0.982,
    "acc_ood": 0.5988,
    "auc_iid": 0.9818333512990985,
    "auc_ood": 0.8017010879586944,
    "mcc_iid": 0.8400949605197195,
    "mcc_ood": 0.7502329990165046,
    "method": "sae_topk",
    "num_latents": 100,
    "k": 10,
    "input_dim": 47,
    "width": 100,
    "n_samples": 10000,
    "seed": 0
  },
  {
    "acc_iid": 0.9532,
    "acc_ood": 0.6488,
    "auc_iid": 0.8207660631328586,
    "auc_ood": 0.775111984448952,
    "mcc_iid": 0.24892928755227303,
    "mcc_ood": 0.32113561817205366,
    "method": "sae_jumprelu",
    "num_latents": 100,
    "k": 10,
    "input_dim": 47,
    "width": 100,
    "n_samples": 10000,
    "seed": 0
  },
  {
    "acc_iid": 0.9726,
    "acc_ood": 0.667,
    "auc_iid": 0.6758435144166575,
    "auc_ood": 0.7233695986231483,
    "mcc_iid": 0.7289531686382165,
    "mcc_ood": 0.6566253917543211,
    "method": "sae_MP",
    "num_latents": 100,
    "k": 10,
    "input_dim": 47,
    "width": 100,
    "n_samples": 10000,
    "seed": 0
  },
  {
    "acc_iid": 0.9896,
    "acc_ood": 0.9296,
    "auc_iid": 0.9970234783576278,
    "auc_ood": 0.9945744526912124,
    "mcc_iid": 0.986596494029596,
    "mcc_ood": 0.9859364894748577,
    "method": "fista_oracle",
    "num_latents": 100,
    "k": 10,
    "input_dim": 47,
    "width": 100,
    "n_samples": 10000,
    "seed": 0
  },
  {
    "acc_iid": 0.9894,
    "acc_ood": 0.9476,
    "auc_iid": 0.9927469017747858,
    "auc_ood": 0.9929057307353455,
    "mcc_iid": 0.9720109026198407,
    "mcc_ood": 0.9660013938101606,
    "method": "dl_fista",
    "num_latents": 100,
    "k": 10,
    "input_dim": 47,
    "width": 100,
    "n_samples": 10000,
    "seed": 0
  },
  {
    "acc_iid": 0.967,
    "acc_ood": 0.6084,
    "auc_iid": 0.9025838972265494,
    "auc_ood": 0.8328279947036286,
    "mcc_iid": 0.6226444078920268,
    "mcc_ood": 0.4338191314227387,
    "method": "softplus_adam",
    "num_latents": 100,
    "k": 10,
    "input_dim": 47,
    "width": 100,
    "n_samples": 10000,
    "seed": 0
  },
  {
    "acc_iid": 0.9536,
    "acc_ood": 0.6538,
    "auc_iid": 0.9792481736113748,
    "auc_ood": 0.8691641166564668,
    "mcc_iid": 0.6750211554277539,
    "mcc_ood": 0.39296149632808225,
    "method": "linear_probe",
    "num_latents": 100,
    "k": 10,
    "input_dim": 47,
    "width": 100,
    "n_samples": 10000,
    "seed": 1
  },
  {
    "acc_iid": 0.968,
    "acc_ood": 0.5826,
    "auc_iid": 0.8901480059889967,
    "auc_ood": 0.8375431901727608,
    "mcc_iid": 0.42880917991072925,
    "mcc_ood": 0.43294685421391355,
    "method": "sae_relu",
    "num_latents": 100,
    "k": 10,
    "input_dim": 47,
    "width": 100,
    "n_samples": 10000,
    "seed": 1
  },
  {
    "acc_iid": 0.9862,
    "acc_ood": 0.6674,
    "auc_iid": 0.9831790696711223,
    "auc_ood": 0.7904046016184065,
    "mcc_iid": 0.8426209014663157,
    "mcc_ood": 0.770483290567163,
    "method": "sae_topk",
    "num_latents": 100,
    "k": 10,
    "input_dim": 47,
    "width": 100,
    "n_samples": 10000,
    "seed": 1
  },
  {
    "acc_iid": 0.9522,
    "acc_ood": 0.6498,
    "auc_iid": 0.7772206102347293,
    "auc_ood": 0.7109732438929756,
    "mcc_iid": 0.2518204603506152,
    "mcc_ood": 0.33231059773061133,
    "method": "sae_jumprelu",
    "num_latents": 100,
    "k": 10,
    "input_dim": 47,
    "width": 100,
    "n_samples": 10000,
    "seed": 1
  },
  {
    "acc_iid": 0.9686,
    "acc_ood": 0.663,
    "auc_iid": 0.70840680627115,
    "auc_ood": 0.7153889415557663,
    "mcc_iid": 0.7287864932469615,
    "mcc_ood": 0.6411912919387359,
    "method": "sae_MP",
    "num_latents": 100,
    "k": 10,
    "input_dim": 47,
    "width": 100,
    "n_samples": 10000,
    "seed": 1
  },
  {
    "acc_iid": 0.9882,
    "acc_ood": 0.9198,
    "auc_iid": 0.9978682922882762,
    "auc_ood": 0.9818348073392293,
    "mcc_iid": 0.9863376107326886,
    "mcc_ood": 0.9832841752062238,
    "method": "fista_oracle",
    "num_latents": 100,
    "k": 10,
    "input_dim": 47,
    "width": 100,
    "n_samples": 10000,
    "seed": 1
  },
  {
    "acc_iid": 0.9884,
    "acc_ood": 0.7432,
    "auc_iid": 0.7422682005262369,
    "auc_ood": 0.7802575210300842,
    "mcc_iid": 0.9259074467662388,
    "mcc_ood": 0.8992057268621793,
    "method": "dl_fista",
    "num_latents": 100,
    "k": 10,
    "input_dim": 47,
    "width": 100,
    "n_samples": 10000,
    "seed": 1
  },
  {
    "acc_iid": 0.9524,
    "acc_ood": 0.5546,
    "auc_iid": 0.8482625836421933,
    "auc_ood": 0.711313085252341,
    "mcc_iid": 0.6567646718720248,
    "mcc_ood": 0.5118413313043579,
    "method": "softplus_adam",
    "num_latents": 100,
    "k": 10,
    "input_dim": 47,
    "width": 100,
    "n_samples": 10000,
    "seed": 1
  },
  {
    "acc_iid": 0.9574,
    "acc_ood": 0.7568,
    "auc_iid": 0.9849423567796382,
    "auc_ood": 0.8902658861471117,
    "mcc_iid": 0.6744005839632292,
    "mcc_ood": 0.403589406912392,
    "method": "linear_probe",
    "num_latents": 100,
    "k": 10,
    "input_dim": 47,
    "width": 100,
    "n_samples": 10000,
    "seed": 2
  },
  {
    "acc_iid": 0.9688,
    "acc_ood": 0.7332,
    "auc_iid": 0.9119891110142195,
    "auc_ood": 0.853252133691316,
    "mcc_iid": 0.41841732074618115,
    "mcc_ood": 0.40760337933800705,
    "method": "sae_relu",
    "num_latents": 100,
    "k": 10,
    "input_dim": 47,
    "width": 100,
    "n_samples": 10000,
    "seed": 2
  },
  {
    "acc_iid": 0.9788,
    "acc_ood": 0.7198,
    "auc_iid": 0.9750555023232215,
    "auc_ood": 0.873550230274609,
    "mcc_iid": 0.8336889048506851,
    "mcc_ood": 0.7341035454185965,
    "method": "sae_topk",
    "num_latents": 100,
    "k": 10,
    "input_dim": 47,
    "width": 100,
    "n_samples": 10000,
    "seed": 2
  },
  {
    "acc_iid": 0.9578,
    "acc_ood": 0.7494,
    "auc_iid": 0.7305456850914362,
    "auc_ood": 0.6919445900471753,
    "mcc_iid": 0.24620060071484332,
    "mcc_ood": 0.31380583594527744,
    "method": "sae_jumprelu",
    "num_latents": 100,
    "k": 10,
    "input_dim": 47,
    "width": 100,
    "n_samples": 10000,
    "seed": 2
  },
  {
    "acc_iid": 0.9726,
    "acc_ood": 0.7858,
    "auc_iid": 0.6545951833295476,
    "auc_ood": 0.6571763651423062,
    "mcc_iid": 0.7320936183489729,
    "mcc_ood": 0.6482079468106023,
    "method": "sae_MP",
    "num_latents": 100,
    "k": 10,
    "input_dim": 47,
    "width": 100,
    "n_samples": 10000,
    "seed": 2
  },
  {
    "acc_iid": 0.986,
    "acc_ood": 0.883,
    "auc_iid": 0.9975673403530392,
    "auc_ood": 0.9957349381199508,
    "mcc_iid": 0.9841760546752358,
    "mcc_ood": 0.9878478534203723,
    "method": "fista_oracle",
    "num_latents": 100,
    "k": 10,
    "input_dim": 47,
    "width": 100,
    "n_samples": 10000,
    "seed": 2
  },
  {
    "acc_iid": 0.9826,
    "acc_ood": 0.9028,
    "auc_iid": 0.9314519111858396,
    "auc_ood": 0.989699702703676,
    "mcc_iid": 0.9396988448316924,
    "mcc_ood": 0.9430016118746036,
    "method": "dl_fista",
    "num_latents": 100,
    "k": 10,
    "input_dim": 47,
    "width": 100,
    "n_samples": 10000,
    "seed": 2
  },
  {
    "acc_iid": 0.9612,
    "acc_ood": 0.712,
    "auc_iid": 0.7496403553889254,
    "auc_ood": 0.678109387441531,
    "mcc_iid": 0.5778246099217478,
    "mcc_ood": 0.4175648285260963,
    "method": "softplus_adam",
    "num_latents": 100,
    "k": 10,
    "input_dim": 47,
    "width": 100,
    "n_samples": 10000,
    "seed": 2
  },
  {
    "acc_iid": 0.9518,
    "acc_ood": 0.63292,
    "auc_iid": 0.9813298231995372,
    "auc_ood": 0.8994626682506244,
    "mcc_iid": 0.6793642782308038,
    "mcc_ood": 0.41010164800399534,
    "method": "linear_probe",
    "num_latents": 100,
    "k": 10,
    "input_dim": 47,
    "width": 100,
    "n_samples": 50000,
    "seed": 0
  },
  {
    "acc_iid": 0.96244,
    "acc_ood": 0.5772,
    "auc_iid": 0.8074543607633294,
    "auc_ood": 0.8635446141185095,
    "mcc_iid": 0.42886984841777237,
    "mcc_ood": 0.43032269419353386,
    "method": "sae_relu",
    "num_latents": 100,
    "k": 10,
    "input_dim": 47,
    "width": 100,
    "n_samples": 50000,
    "seed": 0
  },
  {
    "acc_iid": 0.97812,
    "acc_ood": 0.66048,
    "auc_iid": 0.983775581877522,
    "auc_ood": 0.7878369733466559,
    "mcc_iid": 0.8696432922174838,
    "mcc_ood": 0.8028909921363225,
    "method": "sae_topk",
    "num_latents": 100,
    "k": 10,
    "input_dim": 47,
    "width": 100,
    "n_samples": 50000,
    "seed": 0
  },
  {
    "acc_iid": 0.95192,
    "acc_ood": 0.63292,
    "auc_iid": 0.7490917196028758,
    "auc_ood": 0.649553255688019,
    "mcc_iid": 0.1459746838052614,
    "mcc_ood": 0.3121633274394536,
    "method": "sae_jumprelu",
    "num_latents": 100,
    "k": 10,
    "input_dim": 47,
    "width": 100,
    "n_samples": 50000,
    "seed": 0
  },
  {
    "acc_iid": 0.96652,
    "acc_ood": 0.62368,
    "auc_iid": 0.6041997553787155,
    "auc_ood": 0.624736563603748,
    "mcc_iid": 0.740572021176887,
    "mcc_ood": 0.6779977392019341,
    "method": "sae_MP",
    "num_latents": 100,
    "k": 10,
    "input_dim": 47,
    "width": 100,
    "n_samples": 50000,
    "seed": 0
  },
  {
    "acc_iid": 0.98344,
    "acc_ood": 0.92144,
    "auc_iid": 0.997205732520915,
    "auc_ood": 0.9937247346812923,
    "mcc_iid": 0.9864249878546161,
    "mcc_ood": 0.9858108004978026,
    "method": "fista_oracle",
    "num_latents": 100,
    "k": 10,
    "input_dim": 47,
    "width": 100,
    "n_samples": 50000,
    "seed": 0
  },
  {
    "acc_iid": 0.98312,
    "acc_ood": 0.93092,
    "auc_iid": 0.9936639922516587,
    "auc_ood": 0.9914254154322438,
    "mcc_iid": 0.9723387346398751,
    "mcc_ood": 0.9775896997755841,
    "method": "dl_fista",
    "num_latents": 100,
    "k": 10,
    "input_dim": 47,
    "width": 100,
    "n_samples": 50000,
    "seed": 0
  },
  {
    "acc_iid": 0.93328,
    "acc_ood": 0.50468,
    "auc_iid": 0.8187917607726451,
    "auc_ood": 0.6968466406638879,
    "mcc_iid": 0.7333280263116455,
    "mcc_ood": 0.5499194738222087,
    "method": "softplus_adam",
    "num_latents": 100,
    "k": 10,
    "input_dim": 47,
    "width": 100,
    "n_samples": 50000,
    "seed": 0
  },
  {
    "acc_iid": 0.95736,
    "acc_ood": 0.65064,
    "auc_iid": 0.9803183684671656,
    "auc_ood": 0.8704069933187044,
    "mcc_iid": 0.6789295133692943,
    "mcc_ood": 0.3848333547843659,
    "method": "linear_probe",
    "num_latents": 100,
    "k": 10,
    "input_dim": 47,
    "width": 100,
    "n_samples": 50000,
    "seed": 1
  },
  {
    "acc_iid": 0.97184,
    "acc_ood": 0.59652,
    "auc_iid": 0.8516910942867313,
    "auc_ood": 0.7481248504319388,
    "mcc_iid": 0.4230116269474912,
    "mcc_ood": 0.43884135395418755,
    "method": "sae_relu",
    "num_latents": 100,
    "k": 10,
    "input_dim": 47,
    "width": 100,
    "n_samples": 50000,
    "seed": 1
  },
  {
    "acc_iid": 0.9826,
    "acc_ood": 0.68424,
    "auc_iid": 0.9833547731759021,
    "auc_ood": 0.8020023477001615,
    "mcc_iid": 0.8703452617291267,
    "mcc_ood": 0.8031878675933497,
    "method": "sae_topk",
    "num_latents": 100,
    "k": 10,
    "input_dim": 47,
    "width": 100,
    "n_samples": 50000,
    "seed": 1
  },
  {
    "acc_iid": 0.95808,
    "acc_ood": 0.64756,
    "auc_iid": 0.7446658438254556,
    "auc_ood": 0.5772058620235211,
    "mcc_iid": 0.14244706130648485,
    "mcc_ood": 0.31846173155324325,
    "method": "sae_jumprelu",
    "num_latents": 100,
    "k": 10,
    "input_dim": 47,
    "width": 100,
    "n_samples": 50000,
    "seed": 1
  },
  {
    "acc_iid": 0.97112,
    "acc_ood": 0.65148,
    "auc_iid": 0.6152004742378476,
    "auc_ood": 0.571087331517371,
    "mcc_iid": 0.7675682191150777,
    "mcc_ood": 0.7024530087370143,
    "method": "sae_MP",
    "num_latents": 100,
    "k": 10,
    "input_dim": 47,
    "width": 100,
    "n_samples": 50000,
    "seed": 1
  },
  {
    "acc_iid": 0.98692,
    "acc_ood": 0.92004,
    "auc_iid": 0.9981377342691509,
    "auc_ood": 0.9824860344262797,
    "mcc_iid": 0.9864366535426317,
    "mcc_ood": 0.9829512912679151,
    "method": "fista_oracle",
    "num_latents": 100,
    "k": 10,
    "input_dim": 47,
    "width": 100,
    "n_samples": 50000,
    "seed": 1
  },
  {
    "acc_iid": 0.98508,
    "acc_ood": 0.83236,
    "auc_iid": 0.8968554787131736,
    "auc_ood": 0.9592438489062806,
    "mcc_iid": 0.9277500409736291,
    "mcc_ood": 0.919391034939216,
    "method": "dl_fista",
    "num_latents": 100,
    "k": 10,
    "input_dim": 47,
    "width": 100,
    "n_samples": 50000,
    "seed": 1
  },
  {
    "acc_iid": 0.92488,
    "acc_ood": 0.5194,
    "auc_iid": 0.8619398748307101,
    "auc_ood": 0.7714935416037545,
    "mcc_iid": 0.743979649938736,
    "mcc_ood": 0.5670728385107842,
    "method": "softplus_adam",
    "num_latents": 100,
    "k": 10,
    "input_dim": 47,
    "width": 100,
    "n_samples": 50000,
    "seed": 1
  },
  {
    "acc_iid": 0.95384,
    "acc_ood": 0.75616,
    "auc_iid": 0.9849128736792225,
    "auc_ood": 0.8935762913197975,
    "mcc_iid": 0.6783255393347817,
    "mcc_ood": 0.38731692944757024,
    "method": "linear_probe",
    "num_latents": 100,
    "k": 10,
    "input_dim": 47,
    "width": 100,
    "n_samples": 50000,
    "seed": 2
  },
  {
    "acc_iid": 0.96236,
    "acc_ood": 0.75272,
    "auc_iid": 0.92324367716001,
    "auc_ood": 0.8763762460537838,
    "mcc_iid": 0.41953881215431577,
    "mcc_ood": 0.43278630855948913,
    "method": "sae_relu",
    "num_latents": 100,
    "k": 10,
    "input_dim": 47,
    "width": 100,
    "n_samples": 50000,
    "seed": 2
  },
  {
    "acc_iid": 0.97968,
    "acc_ood": 0.73516,
    "auc_iid": 0.976375172392952,
    "auc_ood": 0.8762926426804237,
    "mcc_iid": 0.8437935223657324,
    "mcc_ood": 0.7837939736868532,
    "method": "sae_topk",
    "num_latents": 100,
    "k": 10,
    "input_dim": 47,
    "width": 100,
    "n_samples": 50000,
    "seed": 2
  },
  {
    "acc_iid": 0.95432,
    "acc_ood": 0.74916,
    "auc_iid": 0.7328355396200507,
    "auc_ood": 0.7187703256421472,
    "mcc_iid": 0.14899155023550664,
    "mcc_ood": 0.31959829964347086,
    "method": "sae_jumprelu",
    "num_latents": 100,
    "k": 10,
    "input_dim": 47,
    "width": 100,
    "n_samples": 50000,
    "seed": 2
  },
  {
    "acc_iid": 0.96296,
    "acc_ood": 0.78544,
    "auc_iid": 0.6254495557197035,
    "auc_ood": 0.5522019706460064,
    "mcc_iid": 0.756375805301365,
    "mcc_ood": 0.6844088520236713,
    "method": "sae_MP",
    "num_latents": 100,
    "k": 10,
    "input_dim": 47,
    "width": 100,
    "n_samples": 50000,
    "seed": 2
  },
  {
    "acc_iid": 0.9838,
    "acc_ood": 0.83152,
    "auc_iid": 0.997125421949654,
    "auc_ood": 0.9956898790625331,
    "mcc_iid": 0.9838350753259641,
    "mcc_ood": 0.9877864737157708,
    "method": "fista_oracle",
    "num_latents": 100,
    "k": 10,
    "input_dim": 47,
    "width": 100,
    "n_samples": 50000,
    "seed": 2
  },
  {
    "acc_iid": 0.98164,
    "acc_ood": 0.87776,
    "auc_iid": 0.9117251858838976,
    "auc_ood": 0.9824388691852393,
    "mcc_iid": 0.9378659332975481,
    "mcc_ood": 0.9449309796291049,
    "method": "dl_fista",
    "num_latents": 100,
    "k": 10,
    "input_dim": 47,
    "width": 100,
    "n_samples": 50000,
    "seed": 2
  },
  {
    "acc_iid": 0.92888,
    "acc_ood": 0.52116,
    "auc_iid": 0.9177958556554844,
    "auc_ood": 0.8818332333693928,
    "mcc_iid": 0.6897541581738436,
    "mcc_ood": 0.5017171656096092,
    "method": "softplus_adam",
    "num_latents": 100,
    "k": 10,
    "input_dim": 47,
    "width": 100,
    "n_samples": 50000,
    "seed": 2
  },
  {
    "acc_iid": 0.95322,
    "acc_ood": 0.63816,
    "auc_iid": 0.9822879578144987,
    "auc_ood": 0.9000011665166517,
    "mcc_iid": 0.6796998378180455,
    "mcc_ood": 0.40908276633802554,
    "method": "linear_probe",
    "num_latents": 100,
    "k": 10,
    "input_dim": 47,
    "width": 100,
    "n_samples": 100000,
    "seed": 0
  },
  {
    "acc_iid": 0.96486,
    "acc_ood": 0.57078,
    "auc_iid": 0.8083925427602219,
    "auc_ood": 0.8421663326332633,
    "mcc_iid": 0.4185186706911695,
    "mcc_ood": 0.436980609568247,
    "method": "sae_relu",
    "num_latents": 100,
    "k": 10,
    "input_dim": 47,
    "width": 100,
    "n_samples": 100000,
    "seed": 0
  },
  {
    "acc_iid": 0.98018,
    "acc_ood": 0.65732,
    "auc_iid": 0.9852428688234066,
    "auc_ood": 0.7879116447644766,
    "mcc_iid": 0.86959498892581,
    "mcc_ood": 0.8030408946900248,
    "method": "sae_topk",
    "num_latents": 100,
    "k": 10,
    "input_dim": 47,
    "width": 100,
    "n_samples": 100000,
    "seed": 0
  },
  {
    "acc_iid": 0.95534,
    "acc_ood": 0.58248,
    "auc_iid": 0.8477745765164639,
    "auc_ood": 0.8208436595659566,
    "mcc_iid": 0.17138369646663196,
    "mcc_ood": 0.3453710366942663,
    "method": "sae_jumprelu",
    "num_latents": 100,
    "k": 10,
    "input_dim": 47,
    "width": 100,
    "n_samples": 100000,
    "seed": 0
  },
  {
    "acc_iid": 0.9676,
    "acc_ood": 0.63898,
    "auc_iid": 0.577803913771095,
    "auc_ood": 0.5655227522752274,
    "mcc_iid": 0.7895520783629938,
    "mcc_ood": 0.7198231524456968,
    "method": "sae_MP",
    "num_latents": 100,
    "k": 10,
    "input_dim": 47,
    "width": 100,
    "n_samples": 100000,
    "seed": 0
  },
  {
    "acc_iid": 0.98562,
    "acc_ood": 0.92286,
    "auc_iid": 0.9978350801012159,
    "auc_ood": 0.9936008240824082,
    "mcc_iid": 0.9863925879220019,
    "mcc_ood": 0.9859789561754108,
    "method": "fista_oracle",
    "num_latents": 100,
    "k": 10,
    "input_dim": 47,
    "width": 100,
    "n_samples": 100000,
    "seed": 0
  },
  {
    "acc_iid": 0.98582,
    "acc_ood": 0.92998,
    "auc_iid": 0.9933137952316032,
    "auc_ood": 0.9907099717971797,
    "mcc_iid": 0.9720162925927441,
    "mcc_ood": 0.9734427627302392,
    "method": "dl_fista",
    "num_latents": 100,
    "k": 10,
    "input_dim": 47,
    "width": 100,
    "n_samples": 100000,
    "seed": 0
  },
  {
    "acc_iid": 0.93594,
    "acc_ood": 0.50524,
    "auc_iid": 0.8634359627290804,
    "auc_ood": 0.7891080844084408,
    "mcc_iid": 0.7101444021181516,
    "mcc_ood": 0.5193739351792397,
    "method": "softplus_adam",
    "num_latents": 100,
    "k": 10,
    "input_dim": 47,
    "width": 100,
    "n_samples": 100000,
    "seed": 0
  },
  {
    "acc_iid": 0.95904,
    "acc_ood": 0.65434,
    "auc_iid": 0.9819270868566073,
    "auc_ood": 0.8703768394599013,
    "mcc_iid": 0.6790879718244446,
    "mcc_ood": 0.3850245953045778,
    "method": "linear_probe",
    "num_latents": 100,
    "k": 10,
    "input_dim": 47,
    "width": 100,
    "n_samples": 100000,
    "seed": 1
  },
  {
    "acc_iid": 0.97092,
    "acc_ood": 0.59206,
    "auc_iid": 0.882294724096966,
    "auc_ood": 0.7710314219334575,
    "mcc_iid": 0.4295876495791458,
    "mcc_ood": 0.4418196718630821,
    "method": "sae_relu",
    "num_latents": 100,
    "k": 10,
    "input_dim": 47,
    "width": 100,
    "n_samples": 100000,
    "seed": 1
  },
  {
    "acc_iid": 0.98348,
    "acc_ood": 0.68028,
    "auc_iid": 0.9866584452812734,
    "auc_ood": 0.7988343834002447,
    "mcc_iid": 0.861475472246025,
    "mcc_ood": 0.8168687001888096,
    "method": "sae_topk",
    "num_latents": 100,
    "k": 10,
    "input_dim": 47,
    "width": 100,
    "n_samples": 100000,
    "seed": 1
  },
  {
    "acc_iid": 0.96042,
    "acc_ood": 0.62836,
    "auc_iid": 0.7727951547361651,
    "auc_ood": 0.7000222493586381,
    "mcc_iid": 0.17778986559299703,
    "mcc_ood": 0.34726667255812904,
    "method": "sae_jumprelu",
    "num_latents": 100,
    "k": 10,
    "input_dim": 47,
    "width": 100,
    "n_samples": 100000,
    "seed": 1
  },
  {
    "acc_iid": 0.97098,
    "acc_ood": 0.6594,
    "auc_iid": 0.7093357858178512,
    "auc_ood": 0.7983068223356329,
    "mcc_iid": 0.7421243268077002,
    "mcc_ood": 0.6710526613648256,
    "method": "sae_MP",
    "num_latents": 100,
    "k": 10,
    "input_dim": 47,
    "width": 100,
    "n_samples": 100000,
    "seed": 1
  },
  {
    "acc_iid": 0.986,
    "acc_ood": 0.92138,
    "auc_iid": 0.9981759612462923,
    "auc_ood": 0.9826084257312199,
    "mcc_iid": 0.9864748952839619,
    "mcc_ood": 0.9828948846309705,
    "method": "fista_oracle",
    "num_latents": 100,
    "k": 10,
    "input_dim": 47,
    "width": 100,
    "n_samples": 100000,
    "seed": 1
  },
  {
    "acc_iid": 0.98558,
    "acc_ood": 0.88008,
    "auc_iid": 0.9382461960932303,
    "auc_ood": 0.9605279972901537,
    "mcc_iid": 0.9427753083567127,
    "mcc_ood": 0.9537027266796447,
    "method": "dl_fista",
    "num_latents": 100,
    "k": 10,
    "input_dim": 47,
    "width": 100,
    "n_samples": 100000,
    "seed": 1
  },
  {
    "acc_iid": 0.94928,
    "acc_ood": 0.50118,
    "auc_iid": 0.8569572374122438,
    "auc_ood": 0.7505839560639342,
    "mcc_iid": 0.7650863404191927,
    "mcc_ood": 0.5943059988853719,
    "method": "softplus_adam",
    "num_latents": 100,
    "k": 10,
    "input_dim": 47,
    "width": 100,
    "n_samples": 100000,
    "seed": 1
  },
  {
    "acc_iid": 0.95306,
    "acc_ood": 0.75484,
    "auc_iid": 0.9848572602693558,
    "auc_ood": 0.8935781843766568,
    "mcc_iid": 0.6788316440885349,
    "mcc_ood": 0.3813501374304875,
    "method": "linear_probe",
    "num_latents": 100,
    "k": 10,
    "input_dim": 47,
    "width": 100,
    "n_samples": 100000,
    "seed": 2
  },
  {
    "acc_iid": 0.96158,
    "acc_ood": 0.75822,
    "auc_iid": 0.9211601750800515,
    "auc_ood": 0.8745568940829466,
    "mcc_iid": 0.41554170776672855,
    "mcc_ood": 0.4353541684295074,
    "method": "sae_relu",
    "num_latents": 100,
    "k": 10,
    "input_dim": 47,
    "width": 100,
    "n_samples": 100000,
    "seed": 2
  },
  {
    "acc_iid": 0.97882,
    "acc_ood": 0.71276,
    "auc_iid": 0.9767879758851647,
    "auc_ood": 0.8737414169548663,
    "mcc_iid": 0.844947730902517,
    "mcc_ood": 0.7890138794292957,
    "method": "sae_topk",
    "num_latents": 100,
    "k": 10,
    "input_dim": 47,
    "width": 100,
    "n_samples": 100000,
    "seed": 2
  },
  {
    "acc_iid": 0.95582,
    "acc_ood": 0.74598,
    "auc_iid": 0.8077765873371532,
    "auc_ood": 0.7639005233392242,
    "mcc_iid": 0.17220602777836078,
    "mcc_ood": 0.3448112999152579,
    "method": "sae_jumprelu",
    "num_latents": 100,
    "k": 10,
    "input_dim": 47,
    "width": 100,
    "n_samples": 100000,
    "seed": 2
  },
  {
    "acc_iid": 0.96362,
    "acc_ood": 0.79352,
    "auc_iid": 0.6513801444394302,
    "auc_ood": 0.5709003587433121,
    "mcc_iid": 0.7567108894670538,
    "mcc_ood": 0.6894531219308736,
    "method": "sae_MP",
    "num_latents": 100,
    "k": 10,
    "input_dim": 47,
    "width": 100,
    "n_samples": 100000,
    "seed": 2
  },
  {
    "acc_iid": 0.98226,
    "acc_ood": 0.85584,
    "auc_iid": 0.9971596668859468,
    "auc_ood": 0.9957089326351263,
    "mcc_iid": 0.9838945569687028,
    "mcc_ood": 0.9878547132620776,
    "method": "fista_oracle",
    "num_latents": 100,
    "k": 10,
    "input_dim": 47,
    "width": 100,
    "n_samples": 100000,
    "seed": 2
  },
  {
    "acc_iid": 0.98082,
    "acc_ood": 0.93426,
    "auc_iid": 0.9077568239490684,
    "auc_ood": 0.987205375845338,
    "mcc_iid": 0.9250464514626713,
    "mcc_ood": 0.9460008777654478,
    "method": "dl_fista",
    "num_latents": 100,
    "k": 10,
    "input_dim": 47,
    "width": 100,
    "n_samples": 100000,
    "seed": 2
  },
  {
    "acc_iid": 0.93848,
    "acc_ood": 0.49992,
    "auc_iid": 0.9083879374924233,
    "auc_ood": 0.8468850415634438,
    "mcc_iid": 0.7699607046555199,
    "mcc_ood": 0.6188757681704462,
    "method": "softplus_adam",
    "num_latents": 100,
    "k": 10,
    "input_dim": 47,
    "width": 100,
    "n_samples": 100000,
    "seed": 2
  }
]