[
  {
    "sae_type": "relu",
    "mean_cosine": 0.36725910139237894,
    "mean_angular_error": 1.19350296268398,
    "mean_norm_ratio": 1.0111948781251907,
    "frac_close": 0.0,
    "num_latents": 5000,
    "k": 10,
    "input_dim": 125,
    "width": 5000,
    "n_samples": 5000,
    "seed": 0
  },
  {
    "sae_type": "topk",
    "mean_cosine": 0.3715366144017489,
    "mean_angular_error": 1.1887815785861786,
    "mean_norm_ratio": 1.0141077737927437,
    "frac_close": 0.0,
    "num_latents": 5000,
    "k": 10,
    "input_dim": 125,
    "width": 5000,
    "n_samples": 5000,
    "seed": 0
  },
  {
    "sae_type": "jumprelu",
    "mean_cosine": 0.32643721593117353,
    "mean_angular_error": 1.2380901986877157,
    "mean_norm_ratio": 0.9906598314404488,
    "frac_close": 0.0,
    "num_latents": 5000,
    "k": 10,
    "input_dim": 125,
    "width": 5000,
    "n_samples": 5000,
    "seed": 0
  },
  {
    "sae_type": "MP",
    "mean_cosine": 0.33581166612031,
    "mean_angular_error": 1.2280637942147241,
    "mean_norm_ratio": 1.0165924770712853,
    "frac_close": 0.0,
    "num_latents": 5000,
    "k": 10,
    "input_dim": 125,
    "width": 5000,
    "n_samples": 5000,
    "seed": 0
  },
  {
    "sae_type": "relu",
    "mean_cosine": 0.368059552384757,
    "mean_angular_error": 1.192633801526986,
    "mean_norm_ratio": 1.0115689046025276,
    "frac_close": 0.0,
    "num_latents": 5000,
    "k": 10,
    "input_dim": 125,
    "width": 5000,
    "n_samples": 5000,
    "seed": 1
  },
  {
    "sae_type": "topk",
    "mean_cosine": 0.36995849250382784,
    "mean_angular_error": 1.1905234166218575,
    "mean_norm_ratio": 1.0142415153980255,
    "frac_close": 0.0,
    "num_latents": 5000,
    "k": 10,
    "input_dim": 125,
    "width": 5000,
    "n_samples": 5000,
    "seed": 1
  },
  {
    "sae_type": "jumprelu",
    "mean_cosine": 0.32614323023602554,
    "mean_angular_error": 1.2383996570887783,
    "mean_norm_ratio": 0.9907945164799691,
    "frac_close": 0.0,
    "num_latents": 5000,
    "k": 10,
    "input_dim": 125,
    "width": 5000,
    "n_samples": 5000,
    "seed": 1
  },
  {
    "sae_type": "MP",
    "mean_cosine": 0.3346032439860331,
    "mean_angular_error": 1.2293670049965797,
    "mean_norm_ratio": 1.0165443883299827,
    "frac_close": 0.0,
    "num_latents": 5000,
    "k": 10,
    "input_dim": 125,
    "width": 5000,
    "n_samples": 5000,
    "seed": 1
  },
  {
    "sae_type": "relu",
    "mean_cosine": 0.3671310319289576,
    "mean_angular_error": 1.1936369634188944,
    "mean_norm_ratio": 1.0116411396741867,
    "frac_close": 0.0,
    "num_latents": 5000,
    "k": 10,
    "input_dim": 125,
    "width": 5000,
    "n_samples": 5000,
    "seed": 2
  },
  {
    "sae_type": "topk",
    "mean_cosine": 0.3718701206673642,
    "mean_angular_error": 1.1883646587981767,
    "mean_norm_ratio": 1.014646239221096,
    "frac_close": 0.0,
    "num_latents": 5000,
    "k": 10,
    "input_dim": 125,
    "width": 5000,
    "n_samples": 5000,
    "seed": 2
  },
  {
    "sae_type": "jumprelu",
    "mean_cosine": 0.3266478522490917,
    "mean_angular_error": 1.23785742321863,
    "mean_norm_ratio": 0.9905671267151832,
    "frac_close": 0.0,
    "num_latents": 5000,
    "k": 10,
    "input_dim": 125,
    "width": 5000,
    "n_samples": 5000,
    "seed": 2
  },
  {
    "sae_type": "MP",
    "mean_cosine": 0.3352724550629109,
    "mean_angular_error": 1.2286408716099109,
    "mean_norm_ratio": 1.0162718547940255,
    "frac_close": 0.0,
    "num_latents": 5000,
    "k": 10,
    "input_dim": 125,
    "width": 5000,
    "n_samples": 5000,
    "seed": 2
  }
]